s3_client/__init__.py
s3_client/main.py
s3_client/s3_core.py
s3_client/utils.py
s3_client-0.1.5.dist-info/licenses/LICENSE
s3_client-0.1.5.dist-info/METADATA
s3_client-0.1.5.dist-info/WHEEL
s3_client-0.1.5.dist-info/entry_points.txt
s3_client-0.1.5.dist-info/top_level.txt
s3_client-0.1.5.dist-info/RECORD
