Metadata-Version: 2.4
Name: s3-client
Version: 0.1.5
Summary: Sample python script to work with Amazon S3.
Author: Thobias Salazar Trevisan
License: MIT License
Project-URL: Homepage, https://github.com/thobiast/s3_client
Project-URL: Source, https://github.com/thobiast/s3_client
Requires-Python: >=3.7
License-File: LICENSE
Requires-Dist: boto3
Requires-Dist: botocore
Requires-Dist: urllib3
Requires-Dist: rich
Dynamic: license-file
